diamond_patterns/__init__.py
diamond_patterns/__meta__.py
diamond_patterns/__pycache__/__init__.cpython-36.pyc
diamond_patterns/__pycache__/__meta__.cpython-36.pyc
diamond_patterns/tests/__init__.py
diamond_patterns/tests/snippet.py
diamond_patterns/tests/test_agile.py
diamond_patterns/tests/test_analysis.py
diamond_patterns/tests/test_ansible.py
diamond_patterns/tests/test_article.py
diamond_patterns/tests/test_beamer.py
diamond_patterns/tests/test_book.py
diamond_patterns/tests/test_chart.py
diamond_patterns/tests/test_organization.py
diamond_patterns/tests/test_outline.py
diamond_patterns/tests/test_presentation.py
diamond_patterns/tests/test_project.py
diamond_patterns/tests/test_python.py
diamond_patterns/tests/test_tufte.py
diamond_patterns/tests/test_website.py
diamond_patterns/tests/__pycache__/__init__.cpython-36.pyc
diamond_patterns/tests/__pycache__/test_agile.cpython-36.pyc
diamond_patterns/tests/__pycache__/test_analysis.cpython-36.pyc
diamond_patterns/tests/__pycache__/test_ansible.cpython-36.pyc
diamond_patterns/tests/__pycache__/test_article.cpython-36.pyc
diamond_patterns/tests/__pycache__/test_beamer.cpython-36.pyc
diamond_patterns/tests/__pycache__/test_book.cpython-36.pyc
diamond_patterns/tests/__pycache__/test_charts.cpython-36.pyc
diamond_patterns/tests/__pycache__/test_organization.cpython-36.pyc
diamond_patterns/tests/__pycache__/test_outline.cpython-36.pyc
diamond_patterns/tests/__pycache__/test_presentation.cpython-36.pyc
diamond_patterns/tests/__pycache__/test_project.cpython-36.pyc
diamond_patterns/tests/__pycache__/test_python.cpython-36.pyc
diamond_patterns/tests/__pycache__/test_tufte.cpython-36.pyc
diamond_patterns/tests/__pycache__/test_website.cpython-36.pyc
diamond_patterns-0.5.3.data/scripts/diamond
diamond_patterns-0.5.3.data/scripts/diamond.cmd
diamond_patterns-0.5.3.dist-info/DESCRIPTION.rst
diamond_patterns-0.5.3.dist-info/METADATA
diamond_patterns-0.5.3.dist-info/RECORD
diamond_patterns-0.5.3.dist-info/WHEEL
diamond_patterns-0.5.3.dist-info/metadata.json
diamond_patterns-0.5.3.dist-info/top_level.txt
