Metadata-Version: 2.0
Name: diamond-patterns
Version: 0.5.3
Summary: Diamond-Patterns are scaffolds for knowledge work.  Use patterns to go faster.
Home-page: https://diamond-patterns.readthedocs.io/
Author: Ian Dennis Miller
Author-email: iandennismiller@gmail.com
License: MIT
Platform: UNKNOWN
Classifier: Development Status :: 4 - Beta
Classifier: Intended Audience :: Developers
Classifier: Intended Audience :: Information Technology
Classifier: Intended Audience :: Science/Research
Classifier: License :: OSI Approved :: MIT License
Classifier: Operating System :: POSIX
Classifier: Operating System :: POSIX :: Linux
Classifier: Operating System :: POSIX :: BSD
Classifier: Operating System :: MacOS :: MacOS X
Classifier: Operating System :: Microsoft :: Windows :: Windows 10
Classifier: Programming Language :: Python :: 3.6
Classifier: Topic :: Office/Business
Requires-Dist: six (==1.11.0)
Requires-Dist: mr.bob (==0.1.2)
Requires-Dist: pyreadline (==2.1)
Requires-Dist: click (==6.6)
Requires-Dist: arrow
Requires-Dist: requests
